jericho_validator/__init__.py
jericho_validator-1.1.12.dist-info/LICENSE
jericho_validator-1.1.12.dist-info/METADATA
jericho_validator-1.1.12.dist-info/WHEEL
jericho_validator-1.1.12.dist-info/top_level.txt
jericho_validator-1.1.12.dist-info/RECORD
