Metadata-Version: 2.1
Name: jericho-validator
Version: 1.1.12
Summary: Validate arbitrary base64-encoded image uploads as incoming data urls while preserving image integrity but removing EXIF and unwanted artifacts and mitigating RCE-exploit potential.
Home-page: https://github.com/hostinfodev/jericho-validator
Author: github.com/hostinfodev
Author-email: aero@recon.us.com
License: UNKNOWN
Project-URL: Example Usage, https://github.com/hostinfodev/jericho-validator/tree/main/example
Platform: UNKNOWN
Classifier: Programming Language :: Python :: 3
Classifier: License :: OSI Approved :: MIT License
Classifier: Operating System :: OS Independent
Requires-Python: >=3.6
License-File: LICENSE
Requires-Dist: Pillow (==9.0.0)
